pyfda/__init__.py
pyfda/filter_factory.py
pyfda/filterbroker.py
pyfda/license_info.md
pyfda/module_versions.md
pyfda/pyfda.qrc
pyfda/pyfda_class.py
pyfda/pyfda_rc.py
pyfda/pyfda_rc_extras.py
pyfda/pyfdax.py
pyfda/qrc_resources.py
pyfda/version.py
pyfda/filter_widgets/__init__.py
pyfda/filter_widgets/bessel.py
pyfda/filter_widgets/butter.py
pyfda/filter_widgets/cheby1.py
pyfda/filter_widgets/cheby2.py
pyfda/filter_widgets/common.py
pyfda/filter_widgets/delay.py
pyfda/filter_widgets/ellip.py
pyfda/filter_widgets/ellip_zero.py
pyfda/filter_widgets/equiripple.py
pyfda/filter_widgets/firwin.py
pyfda/filter_widgets/ma.py
pyfda/filter_widgets/manual.py
pyfda/fixpoint_widgets/__init__.py
pyfda/fixpoint_widgets/default_fx_img.png
pyfda/fixpoint_widgets/fx_ui_wq.py
pyfda/fixpoint_widgets/no_fx_filter.png
pyfda/fixpoint_widgets/fir_df/__init__.py
pyfda/fixpoint_widgets/fir_df/fir_df.png
pyfda/fixpoint_widgets/fir_df/fir_df_amaranth.py
pyfda/fixpoint_widgets/fir_df/fir_df_amaranth_mod.py
pyfda/fixpoint_widgets/fir_df/fir_df_amaranth_ui.py
pyfda/fixpoint_widgets/fir_df/fir_df_pyfixp.py
pyfda/fixpoint_widgets/fir_df/fir_df_pyfixp_ui.py
pyfda/fixpoint_widgets/iir_df1/iir_df1.png
pyfda/fixpoint_widgets/iir_df1/iir_df1_pyfixp.py
pyfda/fixpoint_widgets/iir_df1/iir_df1_pyfixp_ui.py
pyfda/fixpoint_widgets/old/fixpoint_helpers.py
pyfda/fixpoint_widgets/old/delay/delay.png
pyfda/fixpoint_widgets/old/delay/fx_delay.py
pyfda/fixpoint_widgets/old/fir_df/fir_df_amaranth_ui.py
pyfda/fixpoint_widgets/old/fir_df/fir_df_nmigen.py
pyfda/fixpoint_widgets/old/fir_df/fir_df_nmigen_ui.py
pyfda/images/icons/fft.svg
pyfda/images/icons/plot_style-line-mkr.png
pyfda/images/icons/plot_style-line.png
pyfda/images/icons/plot_style-mkr.png
pyfda/images/icons/plot_style-none.png
pyfda/images/icons/plot_style-stem-mkr.png
pyfda/images/icons/plot_style-stem.png
pyfda/images/icons/plot_style-steps-mkr.png
pyfda/images/icons/plot_style-steps.png
pyfda/images/icons/pyfda_icon.png
pyfda/images/icons/pyfda_icon.svg
pyfda-0.9.5.dist-info/AUTHORS.md
pyfda-0.9.5.dist-info/LICENSE.md
pyfda-0.9.5.dist-info/LICENSE_GPLv3.md
pyfda-0.9.5.dist-info/METADATA
pyfda-0.9.5.dist-info/WHEEL
pyfda-0.9.5.dist-info/entry_points.txt
pyfda-0.9.5.dist-info/top_level.txt
pyfda-0.9.5.dist-info/RECORD
