Metadata-Version: 2.1
Name: pyfda
Version: 0.9.5
Summary: Design and analyse discrete time DSP filters with a user-friendly GUI tool. Fixpoint filters in time and frequency domain, too.
Home-page: https://github.com/chipmuenk/pyFDA
Author: Christian Muenker
Author-email: mail07@chipmuenk.de
License: MIT
Keywords: digital,discrete time,filter design,IIR,FIR,GUI
Platform: any
Classifier: Development Status :: 4 - Beta
Classifier: Intended Audience :: Developers
Classifier: Intended Audience :: Education
Classifier: Topic :: Scientific/Engineering
Classifier: Topic :: Education
Classifier: License :: OSI Approved :: MIT License
Classifier: Programming Language :: Python :: 3
Classifier: Programming Language :: Python :: 3.8
Classifier: Programming Language :: Python :: 3.9
Classifier: Programming Language :: Python :: 3.10
Classifier: Programming Language :: Python :: 3.11
Classifier: Programming Language :: Python :: 3.12
License-File: LICENSE.md
License-File: LICENSE_GPLv3.md
License-File: AUTHORS.md
Requires-Dist: numpy<2.0
Requires-Dist: scipy>=1.2.0
Requires-Dist: matplotlib>=3.3
Requires-Dist: pyqt5
Requires-Dist: docutils
Requires-Dist: mplcursors
Requires-Dist: numexpr>=2.8.8
Requires-Dist: markdown
Requires-Dist: amaranth[builtin-yosys]
